dragg/__init__.py
dragg/aggregator.py
dragg/logger.py
dragg/main.py
dragg/mpc_calc.py
dragg/plot.py
dragg/redis_client.py
dragg/devices/__init__.py
dragg/devices/battery.py
dragg/devices/electric_vehicle.py
dragg/devices/hvac.py
dragg/devices/pv.py
dragg/devices/water_heater.py
dragg-2.4.2.dist-info/LICENSE.txt
dragg-2.4.2.dist-info/METADATA
dragg-2.4.2.dist-info/WHEEL
dragg-2.4.2.dist-info/top_level.txt
dragg-2.4.2.dist-info/RECORD
