Metadata-Version: 2.1
Name: dragg
Version: 2.4.2
Author: Aisling Pigott and Cory Mosiman
Author-email: aisling.pigott@colorado.edu
License: MIT
Classifier: Programming Language :: Python :: 3
Classifier: License :: OSI Approved :: MIT License
Classifier: Operating System :: OS Independent
License-File: LICENSE.txt
Requires-Dist: redis
Requires-Dist: pathos
Requires-Dist: cvxpy
Requires-Dist: numpy
Requires-Dist: pandas (==1.5.0)
Requires-Dist: prettytable
Requires-Dist: plotly
Requires-Dist: toml
Requires-Dist: names
